ibquant/__init__.py
ibquant/exceptions.py
ibquant/types.py
ibquant/cli/__init__.py
ibquant/cli/commands.py
ibquant/cli/ib.py
ibquant/core/__init__.py
ibquant/core/base.py
ibquant/core/brute.py
ibquant/core/learner.py
ibquant/core/trader.py
ibquant/factors/__init__.py
ibquant/factors/fundamental/__init__.py
ibquant/factors/momentum/__init__.py
ibquant/factors/momentum/aroon.py
ibquant/factors/momentum/macd.py
ibquant/factors/momentum/momentum.py
ibquant/factors/momentum/rsi.py
ibquant/factors/technical/__init__.py
ibquant/factors/technical/cycle/__init__.py
ibquant/factors/technical/pattern/__init__.py
ibquant/factors/technical/price/__init__.py
ibquant/factors/technical/stats/__init__.py
ibquant/factors/technical/stats/linearregression.py
ibquant/factors/volatility/__init__.py
ibquant/factors/volatility/atr.py
ibquant/factors/volatility/keltnerchannel.py
ibquant/factors/volatility/vixtimer.py
ibquant/flightplan/__init__.py
ibquant/futures/__init__.py
ibquant/futures/utils.py
ibquant/hooks/__init__.py
ibquant/hooks/strategy.py
ibquant/hooks/trader.py
ibquant/io/__init__.py
ibquant/io/downloader.py
ibquant/io/ignore_path.py
ibquant/io/unzip.py
ibquant/loggers/__init__.py
ibquant/loggers/simple.py
ibquant/mixins/__init__.py
ibquant/mixins/account.py
ibquant/mixins/advisor.py
ibquant/mixins/connect.py
ibquant/mixins/contract.py
ibquant/mixins/data.py
ibquant/mixins/orders.py
ibquant/mixins/strategy.py
ibquant/optimize/__init__.py
ibquant/optimize/sweep.py
ibquant/optimize/tearsheet.py
ibquant/parsers/__init__.py
ibquant/parsers/parseconfigs.py
ibquant/performance/__init__.py
ibquant/performance/metrics.py
ibquant/performance/risk.py
ibquant/plotting/__init__.py
ibquant/plotting/marketdepth.py
ibquant/plotting/strategy.py
tests/__init__.py
ibquant-0.1.1.dist-info/LICENSE
ibquant-0.1.1.dist-info/METADATA
ibquant-0.1.1.dist-info/WHEEL
ibquant-0.1.1.dist-info/entry_points.txt
ibquant-0.1.1.dist-info/top_level.txt
ibquant-0.1.1.dist-info/RECORD
