Metadata-Version: 2.1
Name: ibquant
Version: 0.1.1
Summary: A Python Framework for Interactive Brokers TWS API
Author: Justin Goheen
Author-email: 
License: Apache 2.0
Classifier: Environment :: Console
Classifier: Topic :: Scientific/Engineering :: Artificial Intelligence
Classifier: Topic :: Scientific/Engineering :: Information Analysis
Classifier: Topic :: Office/Business :: Financial :: Investment
Classifier: Topic :: Software Development :: User Interfaces
Classifier: Operating System :: OS Independent
Classifier: Programming Language :: Python :: 3.10
License-File: LICENSE
Requires-Dist: ib-insync
Requires-Dist: alphalens-reloaded
Requires-Dist: empyrical-reloaded
Requires-Dist: pyfolio-reloaded
Requires-Dist: zipline-reloaded
Requires-Dist: quantlib
Requires-Dist: pyzmq
Requires-Dist: torch
Requires-Dist: torch-tb-profiler
Requires-Dist: optuna
Requires-Dist: textual
Requires-Dist: rich
Requires-Dist: rich-cli
Requires-Dist: click
Requires-Dist: hydra-core
Requires-Dist: plotly
Requires-Dist: matplotlib
Requires-Dist: fastapi
Requires-Dist: pyarrow
Requires-Dist: xarray
Requires-Dist: beautifulsoup4
Provides-Extra: all
Requires-Dist: ibquant[data,ml] ; extra == 'all'
Provides-Extra: data
Requires-Dist: pyEX ; extra == 'data'
Requires-Dist: Nasdaq-Data-Link ; extra == 'data'
Requires-Dist: yfinance ; extra == 'data'
Provides-Extra: dev
Requires-Dist: black ; extra == 'dev'
Requires-Dist: flake8 ; extra == 'dev'
Requires-Dist: pytest ; extra == 'dev'
Requires-Dist: mypy ; extra == 'dev'
Requires-Dist: coverage ; extra == 'dev'
Requires-Dist: pre-commit ; extra == 'dev'
Requires-Dist: isort ; extra == 'dev'
Provides-Extra: dev-all
Requires-Dist: ibquant[all,dev,docs] ; extra == 'dev-all'
Provides-Extra: docs
Requires-Dist: sphinx ; extra == 'docs'
Requires-Dist: myst-parser ; extra == 'docs'
Requires-Dist: furo ; extra == 'docs'
Provides-Extra: ml
Requires-Dist: scikit-learn ; extra == 'ml'
Requires-Dist: torchserve ; extra == 'ml'
Requires-Dist: pytorch-lightning ; extra == 'ml'
Requires-Dist: ray[rllib] ; extra == 'ml'
Requires-Dist: wandb ; extra == 'ml'
